<VAST version="2.0">
  <Ad id="static">
    <InLine>
      <AdSystem>Static VAST Template</AdSystem>
      <AdTitle>Static VAST Tag</AdTitle>
      <Creatives>
        <Creative>
          <Linear>
            <Duration>00:00:05</Duration>
<VideoClicks>

              <ClickThrough>https://shope.ee/4pdNvqk4vo</ClickThrough>

              <ClickTracking>https://shope.ee/4pdNvqk4vo?r=[REGULATIONS]&gdpr=[GDPRCONSENT]&pu=[PAGEURL]&da=[DEVICEUA]</ClickTracking>

            </VideoClicks>
          
            <MediaFiles>
              <MediaFile a href="https://shope.ee/4pdNvqk4vo" type="video/mp4" bitrate="300" width="640" height="360">
             https://driveas.my.id/stream/360/hSECEAmIrDLuSKM.mp4
              </MediaFile>
            </MediaFiles>
            
           </Linear>
        </Creative>
      </Creatives>
    </InLine>
  </Ad>
</VAST>
